readsltext/__init__.py
readsltext/readsltext.py
readsltext-0.0.6.dist-info/DESCRIPTION.rst
readsltext-0.0.6.dist-info/METADATA
readsltext-0.0.6.dist-info/RECORD
readsltext-0.0.6.dist-info/WHEEL
readsltext-0.0.6.dist-info/entry_points.txt
readsltext-0.0.6.dist-info/metadata.json
readsltext-0.0.6.dist-info/top_level.txt
