Metadata-Version: 2.0
Name: readsltext
Version: 0.0.6
Summary: GPLv3/Python3/CLI text format to annotate texts and produce easy-to-read versions of them
Home-page: https://github.com/suizokukan/readsltext
Author: Xavier Faure (suizokukan / 94.23.197.37)
Author-email: suizokukan@orange.fr
License: GPL-3.0
Keywords: language text
Platform: UNKNOWN
Classifier: Development Status :: 2 - Pre-Alpha
Classifier: Intended Audience :: Education
Classifier: Topic :: Utilities
Classifier: License :: OSI Approved :: GNU General Public License v3 (GPLv3)
Classifier: Programming Language :: Python :: 3
